<?xml version="1.0" encoding="UTF-8"?>
<openerp>
    <data>
        <record id="view_purchase_requisition_form_ext" model="ir.ui.view">
            <field name="name">view.purchase.requisition.form.ext</field>
            <field name="inherit_id" ref="purchase_requisition.view_purchase_requisition_form" />
            <field name="model">purchase.requisition</field>
            <field name="arch" type="xml">
                <data>
                	<field name="company_id" position="after" >
                		<field name="ref_sale_order_id" options="{'limit': 10, 'create': false, 'create_edit': false}"/>
                    </field>	
				</data>
            </field>
        </record>   
    </data>
</openerp>
